CTkSpinbox/__init__.py
CTkSpinbox/ctkspinbox.py
CTkSpinbox-1.4.0.dist-info/LICENSE
CTkSpinbox-1.4.0.dist-info/METADATA
CTkSpinbox-1.4.0.dist-info/WHEEL
CTkSpinbox-1.4.0.dist-info/top_level.txt
CTkSpinbox-1.4.0.dist-info/RECORD
