Metadata-Version: 2.1
Name: CTkSpinbox
Version: 1.4.0
Summary: A custom spinbox widget for customtkinter.
Home-page: https://github.com/Sheikh-Rashdan/CTkSpinbox
Author: Sheikh Rashdan
Author-email: sheikhmohamedrashdan@gmail.com
Project-URL: Bug Tracker, https://github.com/Sheikh-Rashdan/CTkSpinbox/issues
Classifier: Programming Language :: Python :: 3
Classifier: License :: OSI Approved :: MIT License
Classifier: Operating System :: OS Independent
Requires-Python: >=3.6
License-File: LICENSE
